[
  {
    "id": "68",
    "nombre": "Roberto",
    "apellido": "Fernández",
    "telefono": "+56912345678",
    "club": "Club de Tenis Valparaíso",
    "torneo": "Copa Litoral 2023",
    "categoria": "1ª Categoría",
    "año": 2023,
    "estado": "finalizado",
    "partidosJugados": 5,
    "partidosGanados": 4,
    "partidosPerdidos": 1,
    "ranking": 2,
    "tipoSocio": "socio"
  },
  {
    "id": "69",
    "nombre": "Carmen",
    "apellido": "Vega",
    "telefono": "+56987654321",
    "club": "Club de Tenis Quilpué",
    "torneo": "Copa Litoral 2023",
    "categoria": "1ª Categoría",
    "año": 2023,
    "estado": "finalizado",
    "partidosJugados": 4,
    "partidosGanados": 2,
    "partidosPerdidos": 2,
    "ranking": 3,
    "tipoSocio": "general"
  },
  {
    "id": "70",
    "nombre": "Diego",
    "apellido": "Herrera",
    "telefono": "+56955667788",
    "club": "Club de Tenis San Antonio",
    "torneo": "Copa Litoral 2023",
    "categoria": "1ª Categoría",
    "año": 2023,
    "estado": "finalizado",
    "partidosJugados": 4,
    "partidosGanados": 1,
    "partidosPerdidos": 3,
    "ranking": 4,
    "tipoSocio": "socio"
  },
  {
    "id": "71",
    "nombre": "Francisca",
    "apellido": "Rojas",
    "telefono": "+56911223344",
    "club": "Club de Tenis Viña del Mar",
    "torneo": "Copa Litoral 2023",
    "categoria": "1ª Categoría",
    "año": 2023,
    "estado": "finalizado",
    "partidosJugados": 3,
    "partidosGanados": 0,
    "partidosPerdidos": 3,
    "ranking": 5,
    "tipoSocio": "general"
  },
  {
    "id": "72",
    "nombre": "Andrés",
    "apellido": "Castillo",
    "telefono": "+56933445566",
    "club": "Club de Tenis Valparaíso",
    "torneo": "Copa Litoral 2023",
    "categoria": "1ª Categoría",
    "año": 2023,
    "estado": "finalizado",
    "partidosJugados": 4,
    "partidosGanados": 2,
    "partidosPerdidos": 2,
    "ranking": 6,
    "tipoSocio": "socio"
  },
  {
    "id": "73",
    "nombre": "Valentina",
    "apellido": "Soto",
    "telefono": "+56977889900",
    "club": "Club de Tenis Quilpué",
    "torneo": "Copa Litoral 2023",
    "categoria": "1ª Categoría",
    "año": 2023,
    "estado": "finalizado",
    "partidosJugados": 3,
    "partidosGanados": 1,
    "partidosPerdidos": 2,
    "ranking": 7,
    "tipoSocio": "general"
  },
  {
    "id": "74",
    "nombre": "Matías",
    "apellido": "Bravo",
    "telefono": "+56944556677",
    "club": "Club de Tenis San Antonio",
    "torneo": "Copa Litoral 2023",
    "categoria": "1ª Categoría",
    "año": 2023,
    "estado": "finalizado",
    "partidosJugados": 4,
    "partidosGanados": 3,
    "partidosPerdidos": 1,
    "ranking": 8,
    "tipoSocio": "socio"
  },
  {
    "id": "75",
    "nombre": "Isidora",
    "apellido": "Mendoza",
    "telefono": "+56966778899",
    "club": "Club de Tenis Viña del Mar",
    "torneo": "Copa Litoral 2023",
    "categoria": "1ª Categoría",
    "año": 2023,
    "estado": "finalizado",
    "partidosJugados": 3,
    "partidosGanados": 0,
    "partidosPerdidos": 3,
    "ranking": 9,
    "tipoSocio": "general"
  },
  {
    "id": "76",
    "nombre": "Sebastián",
    "apellido": "Parra",
    "telefono": "+56988990011",
    "club": "Club de Tenis Valparaíso",
    "torneo": "Copa Litoral 2023",
    "categoria": "2ª Categoría",
    "año": 2023,
    "estado": "finalizado",
    "partidosJugados": 5,
    "partidosGanados": 5,
    "partidosPerdidos": 0,
    "ranking": 1,
    "tipoSocio": "socio"
  },
  {
    "id": "77",
    "nombre": "Camila",
    "apellido": "Torres",
    "telefono": "+56911223344",
    "club": "Club de Tenis Quilpué",
    "torneo": "Copa Litoral 2023",
    "categoria": "2ª Categoría",
    "año": 2023,
    "estado": "finalizado",
    "partidosJugados": 4,
    "partidosGanados": 3,
    "partidosPerdidos": 1,
    "ranking": 2,
    "tipoSocio": "general"
  }
]
